clifford/__init__.py
clifford/_bit_helpers.py
clifford/_blademap.py
clifford/_conformal_layout.py
clifford/_frame.py
clifford/_layout.py
clifford/_layout_helpers.py
clifford/_multivector.py
clifford/_mvarray.py
clifford/_numba_utils.py
clifford/_parser.py
clifford/_settings.py
clifford/_version.py
clifford/caching.py
clifford/cga.py
clifford/code_gen.py
clifford/dg3c.py
clifford/dpga.py
clifford/g2.py
clifford/g2c.py
clifford/g3.py
clifford/g3_1.py
clifford/g3c.py
clifford/g4.py
clifford/gac.py
clifford/io.py
clifford/operator.py
clifford/pga.py
clifford/pga2d.py
clifford/sta.py
clifford/taylor_expansions.py
clifford/transformations.py
clifford/numba/__init__.py
clifford/numba/_layout.py
clifford/numba/_multivector.py
clifford/numba/_overload_call.py
clifford/test/__init__.py
clifford/test/test_algebra_initialisation.py
clifford/test/test_aliases.py
clifford/test/test_bit_helpers.py
clifford/test/test_cga.py
clifford/test/test_clifford.py
clifford/test/test_complex.py
clifford/test/test_degenerate.py
clifford/test/test_dg3c.py
clifford/test/test_dpga.py
clifford/test/test_function_cache.py
clifford/test/test_g3c_CUDA.py
clifford/test/test_g3c_tools.py
clifford/test/test_io.py
clifford/test/test_layout.py
clifford/test/test_layout_helpers.py
clifford/test/test_multivector_inverse.py
clifford/test/test_numba_extensions.py
clifford/test/test_parser.py
clifford/test/test_tools.py
clifford/test/test_tools_classify.py
clifford/test/test_transformations.py
clifford/test/test_trig_functions.py
clifford/tools/__init__.py
clifford/tools/classify.py
clifford/tools/point_processing.py
clifford/tools/g3/__init__.py
clifford/tools/g3c/GAOnline.py
clifford/tools/g3c/__init__.py
clifford/tools/g3c/cost_functions.py
clifford/tools/g3c/cuda.py
clifford/tools/g3c/cuda_products.py
clifford/tools/g3c/model_matching.py
clifford/tools/g3c/object_clustering.py
clifford/tools/g3c/object_fitting.py
clifford/tools/g3c/rotor_estimation.py
clifford/tools/g3c/rotor_parameterisation.py
clifford-1.5.1.dist-info/licenses/LICENSE.txt
clifford-1.5.1.dist-info/METADATA
clifford-1.5.1.dist-info/WHEEL
clifford-1.5.1.dist-info/top_level.txt
clifford-1.5.1.dist-info/RECORD
