Metadata-Version: 2.4
Name: clifford
Version: 1.5.1
Summary: Numerical Geometric Algebra Module
Home-page: http://clifford.readthedocs.io
Author: Robert Kern
Maintainer: Alex Arsenovic
Maintainer-email: alexarsenovic@gmail.com
License: bsd
Project-URL: Bug Tracker, https://github.com/pygae/clifford/issues
Project-URL: Source Code, https://github.com/pygae/clifford
Classifier: Intended Audience :: Science/Research
Classifier: Topic :: Scientific/Engineering :: Mathematics
Classifier: License :: OSI Approved :: BSD License
Classifier: Programming Language :: Python :: 3
Classifier: Programming Language :: Python :: 3.5
Classifier: Programming Language :: Python :: 3.6
Classifier: Programming Language :: Python :: 3.7
Classifier: Programming Language :: Python :: 3.8
Requires-Python: >=3.5
License-File: LICENSE.txt
Requires-Dist: numpy>=1.17
Requires-Dist: scipy
Requires-Dist: numba>0.46
Requires-Dist: h5py
Requires-Dist: sparse
Dynamic: author
Dynamic: classifier
Dynamic: description
Dynamic: description-content-type
Dynamic: home-page
Dynamic: license
Dynamic: license-file
Dynamic: maintainer
Dynamic: maintainer-email
Dynamic: project-url
Dynamic: requires-dist
Dynamic: requires-python
Dynamic: summary
